test/__init__.py
test/modules/__init__.py
test/modules/conftest.py
test/modules/test_dshw_module.py
test/modules/utils/__init__.py
test/modules/utils/fixtures.py
test/modules/utils/r_model.py
torches/__init__.py
torches/loaders/__init__.py
torches/modules/__init__.py
torches/modules/dshw_module.py
torches/utils/__init__.py
torches/utils/modelparams.py
torches/utils/seasonality.py
torch_es-0.0.1.dist-info/LICENSE
torch_es-0.0.1.dist-info/METADATA
torch_es-0.0.1.dist-info/WHEEL
torch_es-0.0.1.dist-info/top_level.txt
torch_es-0.0.1.dist-info/RECORD
