Metadata-Version: 2.1
Name: torch-es
Version: 0.0.1
Summary: Double Seasonal Exponential Smoothing using PyTorch + ES-RNN capabilities on top
Home-page: https://github.com/vshulyak/torch-es
Author: Vladimir Shulyak
Author-email: vladimir@shulyak.net
License: UNKNOWN
Platform: UNKNOWN
Classifier: Programming Language :: Python :: 3
Classifier: License :: OSI Approved :: MIT License
Classifier: Operating System :: OS Independent
Requires-Dist: torch (>=1.0.0)
Requires-Dist: numpy (>=1.16.0)
